{
  "componentId" : "cf59a25b-ec6f-46d2-8e07-d18d4c7e7e48",
  "name" : "/com/force/goto/globalDealWizard",
  "tagName" : "c-global-deal-wizard",
  "type" : "Block",
  "pageStructureElement" : true,
  "fieldDetailsElement" : false,
  "elements" : [ {
    "componentId" : "ba34bfcf-0f8b-4188-a1f0-7116cf85c359",
    "type" : "component::23229240-c74c-407d-97be-9bddb587e0cc",
    "label" : "Configure Bundle & Teams",
    "properties" : [ ],
    "parameters" : [ {
      "name" : "title",
      "value" : "Configure Bundle & Teams",
      "comparisonType" : "equals",
      "default" : true
    } ],
    "elements" : [ {
      "type" : "content",
      "elements" : [ {
        "componentId" : "d6a7861a-b4a5-4fe7-ac81-e17e59202204",
        "type" : "component::23229240-c74c-407d-97be-9bddb587e0cc",
        "label" : "Bundle Name & Type",
        "properties" : [ ],
        "parameters" : [ {
          "name" : "title",
          "value" : "Bundle Name & Type",
          "comparisonType" : "equals",
          "default" : true
        } ],
        "elements" : [ {
          "type" : "content",
          "elements" : [ {
            "componentId" : "767bc831-70c0-4bae-9b8e-1375fafbb15e",
            "type" : "component::2e0414b9-dc7a-4678-ac44-ffa2072e63f2",
            "label" : "LightningRecordEditForm",
            "properties" : [ ],
            "parameters" : [ {
              "name" : "objectApiName",
              "value" : "Multi_Entity_Deal__c",
              "comparisonType" : "equals",
              "default" : true
            } ],
            "elements" : [ {
              "type" : "content",
              "elements" : [ {
                "componentId" : "42d06e82-184f-4643-9925-70957bf343e4",
                "type" : "component::5cd71547-c934-470c-9115-a10fe7f0307f",
                "label" : "Bundle Name",
                "properties" : [ ],
                "parameters" : [ {
                  "name" : "class",
                  "value" : "slds-form-element",
                  "comparisonType" : "contains",
                  "default" : false
                }, {
                  "name" : "label",
                  "value" : "Bundle Name",
                  "comparisonType" : "equals",
                  "default" : true
                }, {
                  "name" : "type",
                  "value" : "text",
                  "comparisonType" : "equals",
                  "default" : false
                } ],
                "elements" : [ ]
              } ]
            } ]
          } ]
        } ]
      } ]
    } ]
  } ]
}